elkpy/__init__.py
elkpy/audiographcontroller.py
elkpy/audioroutingcontroller.py
elkpy/cvgatecontroller.py
elkpy/events.py
elkpy/grpc_gen.py
elkpy/keyboardcontroller.py
elkpy/midicontroller.py
elkpy/notificationcontroller.py
elkpy/osccontroller.py
elkpy/parametercontroller.py
elkpy/programcontroller.py
elkpy/sessioncontroller.py
elkpy/sushi_info_types.py
elkpy/sushicontroller.py
elkpy/sushierrors.py
elkpy/sushiprocessor.py
elkpy/systemcontroller.py
elkpy/timingcontroller.py
elkpy/transportcontroller.py
elkpy-1.2.3.dist-info/COPYING
elkpy-1.2.3.dist-info/LICENSE
elkpy-1.2.3.dist-info/METADATA
elkpy-1.2.3.dist-info/WHEEL
elkpy-1.2.3.dist-info/top_level.txt
elkpy-1.2.3.dist-info/RECORD
