Metadata-Version: 2.2
Name: elkpy
Version: 1.2.3
Summary: A basic controller for sushi using gRPC
Home-page: https://github.com/elkaudio/elkpy
Author: Ruben Svensson
Author-email: Maxime Gendebien <max@elk.audio>, Ruben Svensson <ruben@elk.audio>
Project-URL: Homepage, https://github.com/elkaudio/elkpy
Project-URL: Bug Tracker, https://github.com/elkaudio/elkpy/issues
Classifier: Programming Language :: Python :: 3
Classifier: Operating System :: OS Independent
Classifier: Intended Audience :: Developers
Classifier: License :: OSI Approved :: GNU General Public License v3 (GPLv3)
Requires-Python: >=3.7
License-File: LICENSE
License-File: COPYING
Requires-Dist: protobuf
Requires-Dist: grpcio
Requires-Dist: grpcio-tools
